ceg/__init__.py
ceg/api.py
ceg/arg_parser.py
ceg/ceg.py
ceg/cli.py
ceg/exceptions.py
ceg/logger.py
ceg/misc.py
ceg-0.5.4.dist-info/LICENSE
ceg-0.5.4.dist-info/METADATA
ceg-0.5.4.dist-info/WHEEL
ceg-0.5.4.dist-info/entry_points.txt
ceg-0.5.4.dist-info/RECORD
