Metadata-Version: 2.1
Name: ceg
Version: 0.5.4
Summary: A simple gist crud utility.
Home-page: https://www.github.com/justaus3r/ceg
License: GPL-3.0-or-later
Keywords: gist,cli,api
Author: Justaus3r
Author-email: x-neron@pm.me
Requires-Python: >=3.10,<4.0
Classifier: Development Status :: 5 - Production/Stable
Classifier: Environment :: Console
Classifier: License :: OSI Approved :: GNU General Public License v3 or later (GPLv3+)
Classifier: Operating System :: OS Independent
Classifier: Programming Language :: Python :: 3
Classifier: Programming Language :: Python :: 3.10
Classifier: Programming Language :: Python :: 3.11
Classifier: Programming Language :: Python :: 3.12
Classifier: Programming Language :: Python :: Implementation :: CPython
Classifier: Topic :: Internet :: WWW/HTTP
Classifier: Topic :: Software Development :: Libraries :: Python Modules
Requires-Dist: requests (>=2.28.1,<3.0.0)
Requires-Dist: rich (>=12.5.1,<13.0.0)
Project-URL: Repository, https://www.github.com/justaus3r/ceg
